mkdocstrings_handlers/typescript/__init__.py
mkdocstrings_handlers/typescript/_internal/__init__.py
mkdocstrings_handlers/typescript/_internal/config.py
mkdocstrings_handlers/typescript/_internal/debug.py
mkdocstrings_handlers/typescript/_internal/handler.py
mkdocstrings_handlers/typescript/py.typed
mkdocstrings_handlers/typescript/templates/material/_base/accessor.html.jinja
mkdocstrings_handlers/typescript/templates/material/_base/call_signature.html.jinja
mkdocstrings_handlers/typescript/templates/material/_base/children.html.jinja
mkdocstrings_handlers/typescript/templates/material/_base/class.html.jinja
mkdocstrings_handlers/typescript/templates/material/_base/constructor.html.jinja
mkdocstrings_handlers/typescript/templates/material/_base/constructor_signature.html.jinja
mkdocstrings_handlers/typescript/templates/material/_base/data.html.jinja
mkdocstrings_handlers/typescript/templates/material/_base/dispatch.html.jinja
mkdocstrings_handlers/typescript/templates/material/_base/enum.html.jinja
mkdocstrings_handlers/typescript/templates/material/_base/enum_member.html.jinja
mkdocstrings_handlers/typescript/templates/material/_base/function.html.jinja
mkdocstrings_handlers/typescript/templates/material/_base/interface.html.jinja
mkdocstrings_handlers/typescript/templates/material/_base/method.html.jinja
mkdocstrings_handlers/typescript/templates/material/_base/module.html.jinja
mkdocstrings_handlers/typescript/templates/material/_base/namespace.html.jinja
mkdocstrings_handlers/typescript/templates/material/_base/project.html.jinja
mkdocstrings_handlers/typescript/templates/material/_base/property.html.jinja
mkdocstrings_handlers/typescript/templates/material/_base/reference.html.jinja
mkdocstrings_handlers/typescript/templates/material/_base/type.html.jinja
mkdocstrings_handlers/typescript/templates/material/_base/type_alias.html.jinja
mkdocstrings_handlers/typescript/templates/material/_base/variable.html.jinja
mkdocstrings_typescript-0.1.0.dist-info/METADATA
mkdocstrings_typescript-0.1.0.dist-info/WHEEL
mkdocstrings_typescript-0.1.0.dist-info/entry_points.txt
mkdocstrings_typescript-0.1.0.dist-info/licenses/LICENSE
mkdocstrings_typescript-0.1.0.dist-info/RECORD
