Metadata-Version: 2.4
Name: mkdocstrings-typescript
Version: 0.1.0
Summary: A Typescript handler for mkdocstrings.
Author-Email: =?utf-8?q?Timoth=C3=A9e_Mazzucotelli?= <dev@pawamoy.fr>
License-Expression: ISC
License-File: LICENSE
Classifier: Development Status :: 4 - Beta
Classifier: Intended Audience :: Developers
Classifier: Programming Language :: Python
Classifier: Programming Language :: Python :: 3
Classifier: Programming Language :: Python :: 3 :: Only
Classifier: Programming Language :: Python :: 3.10
Classifier: Programming Language :: Python :: 3.11
Classifier: Programming Language :: Python :: 3.12
Classifier: Programming Language :: Python :: 3.13
Classifier: Programming Language :: Python :: 3.14
Classifier: Topic :: Documentation
Classifier: Topic :: Software Development
Classifier: Topic :: Utilities
Classifier: Typing :: Typed
Project-URL: Homepage, https://mkdocstrings.github.io/typescript
Project-URL: Documentation, https://mkdocstrings.github.io/typescript
Project-URL: Changelog, https://mkdocstrings.github.io/typescript/changelog
Project-URL: Repository, https://github.com/mkdocstrings/typescript
Project-URL: Issues, https://github.com/mkdocstrings/typescript/issues
Project-URL: Discussions, https://github.com/mkdocstrings/typescript/discussions
Project-URL: Gitter, https://gitter.im/mkdocstrings/typescript
Project-URL: Funding, https://github.com/sponsors/pawamoy
Requires-Python: >=3.10
Requires-Dist: mkdocstrings>=0.28.3
Requires-Dist: griffe-typedoc>=0.1
